LICENSE.txt
MANIFEST.in
README.rst
setup.cfg
setup.py
HydroLM.egg-info/PKG-INFO
HydroLM.egg-info/SOURCES.txt
HydroLM.egg-info/dependency_links.txt
HydroLM.egg-info/requires.txt
HydroLM.egg-info/top_level.txt
hydrolm/__init__.py
hydrolm/lm.py
hydrolm/util.py
hydrolm/datasets/__init__.py
hydrolm/tests/__init__.py
hydrolm/tests/test_regressions.py