Metadata-Version: 1.1
Name: HydroLM
Version: 1.0.6
Summary: Class and functions to do linear regressions for hydrology
Home-page: https://github.com/mullenkamp/HydroLM
Author: Mike Kittridge
Author-email: mullenkamp1@gmail.com
License: UNKNOWN
Keywords: reference et
Platform: UNKNOWN
Classifier: Development Status :: 3 - Alpha
Classifier: Intended Audience :: Developers
Classifier: Topic :: Software Development :: Build Tools
Classifier: License :: OSI Approved :: Apache Software License
Classifier: Programming Language :: Python :: 2
Classifier: Programming Language :: Python :: 2.7
Classifier: Programming Language :: Python :: 3
Classifier: Programming Language :: Python :: 3.4
Classifier: Programming Language :: Python :: 3.5
Classifier: Programming Language :: Python :: 3.6
